pyvenDF/__init__.py
pyvenDF/cli.py
pyvenDF/router.py
pyvenDF/server.py
pyvenDF/utils.py
pyvenDF/templates/__init__.py
pyvenDF/templates/routes.py
pyvenDF/templates/views.py
pyvendf-0.1.3.dist-info/licenses/LICENSE
pyvendf-0.1.3.dist-info/METADATA
pyvendf-0.1.3.dist-info/WHEEL
pyvendf-0.1.3.dist-info/entry_points.txt
pyvendf-0.1.3.dist-info/top_level.txt
pyvendf-0.1.3.dist-info/RECORD
