Metadata-Version: 2.4
Name: pyvenDF
Version: 0.1.3
Summary: A lightweight Python web framework
Author: LESLIE CHEGHE NJUH
License: MIT
Classifier: Programming Language :: Python :: 3
License-File: LICENSE
Dynamic: author
Dynamic: classifier
Dynamic: description-content-type
Dynamic: license
Dynamic: license-file
Dynamic: summary
